pairdist/__init__.py
pairdist/_astropy_init.py
pairdist/_compiler.c
pairdist/_compiler.cpython-36m-darwin.so
pairdist/conftest.py
pairdist/cython_version.py
pairdist/example_c.c
pairdist/example_c.cpython-36m-darwin.so
pairdist/example_mod.py
pairdist/version.py
pairdist/data/README.rst
pairdist/example_subpkg/__init__.py
pairdist/example_subpkg/setup_package.py
pairdist/example_subpkg/tests/__init__.py
pairdist/extern/__init__.py
pairdist/tests/__init__.py
pairdist/tests/coveragerc
pairdist/tests/setup_package.py
pairdist/tests/test_example.py
pairdist/utils/__init__.py
pairdist/utils/tests/__init__.py
pairdist-0.0.dev3.dist-info/METADATA
pairdist-0.0.dev3.dist-info/RECORD
pairdist-0.0.dev3.dist-info/WHEEL
pairdist-0.0.dev3.dist-info/entry_points.txt
pairdist-0.0.dev3.dist-info/top_level.txt
