Metadata-Version: 2.1
Name: pairdist
Version: 0.0.dev3
Summary: Pairwise distances
Home-page: https://github.com/clusterfunc/pairdist
Author: Manodeep Sinha
Author-email: manodeep@gmail.com
License: BSD 3-Clause
Platform: UNKNOWN
Requires-Python: >=3.5
Requires-Dist: astropy
